tiffdata/__init__.py
tiffdata/version.txt
tiffdata/enumerations/__init__.py
tiffdata/enumerations/cleanfaxdata.py
tiffdata/enumerations/compression.py
tiffdata/enumerations/datatype.py
tiffdata/enumerations/exiftag.py
tiffdata/enumerations/extrasamples.py
tiffdata/enumerations/fillorder.py
tiffdata/enumerations/format.py
tiffdata/enumerations/gpstag.py
tiffdata/enumerations/indexed.py
tiffdata/enumerations/inkset.py
tiffdata/enumerations/interoperabilitytag.py
tiffdata/enumerations/jpeglosslesspredictors.py
tiffdata/enumerations/jpegprocess.py
tiffdata/enumerations/newsubfiletype.py
tiffdata/enumerations/oldsubfiletype.py
tiffdata/enumerations/orientation.py
tiffdata/enumerations/photometricinterpretation.py
tiffdata/enumerations/planarconfiguration.py
tiffdata/enumerations/predictor.py
tiffdata/enumerations/resolutionunit.py
tiffdata/enumerations/sampleformat.py
tiffdata/enumerations/t4options.py
tiffdata/enumerations/t6options.py
tiffdata/enumerations/thresholding.py
tiffdata/enumerations/tifftag.py
tiffdata/enumerations/ycbcrpositioning.py
tiffdata/exceptions/__init__.py
tiffdata/logging/__init__.py
tiffdata/structures/__init__.py
tiffdata/structures/attributes.py
tiffdata/structures/information.py
tiffdata/structures/offset.py
tiffdata/structures/file/__init__.py
tiffdata/structures/file/base.py
tiffdata/structures/file/container.py
tiffdata/structures/file/data.py
tiffdata/structures/file/ifd.py
tiffdata/structures/file/strip.py
tiffdata/structures/file/tag.py
tiffdata/structures/file/tile.py
tiffdata/types/__init__.py
tiffdata/utilities/__init__.py
tiffdata/utilities/file.py
tiffdata-0.5.6.dist-info/METADATA
tiffdata-0.5.6.dist-info/WHEEL
tiffdata-0.5.6.dist-info/top_level.txt
tiffdata-0.5.6.dist-info/zip-safe
tiffdata-0.5.6.dist-info/RECORD
