Metadata-Version: 2.4
Name: tiffdata
Version: 0.5.6
Summary: Streamlined TIFF image metadata parsing and updating.
Author: Daniel Sissman
License-Expression: MIT
Project-URL: documentation, https://github.com/bluebinary/tiffdata/blob/main/README.md
Project-URL: changelog, https://github.com/bluebinary/tiffdata/blob/main/CHANGELOG.md
Project-URL: repository, https://github.com/bluebinary/tiffdata
Project-URL: issues, https://github.com/bluebinary/tiffdata/issues
Project-URL: homepage, https://github.com/bluebinary/tiffdata
Keywords: image,metadata,tiff,data
Platform: any
Classifier: Programming Language :: Python :: 3
Classifier: Programming Language :: Python :: 3.10
Classifier: Programming Language :: Python :: 3.11
Classifier: Programming Language :: Python :: 3.12
Classifier: Programming Language :: Python :: 3.13
Requires-Python: >=3.10
Requires-Dist: enumerific>=1.0.5
Requires-Dist: caselessly>=1.0.0
Requires-Dist: deliciousbytes>=1.0.4
Requires-Dist: tabulicious>=0.5.0
Provides-Extra: development
Requires-Dist: black; extra == "development"
Requires-Dist: pytest; extra == "development"
Requires-Dist: pytest-codeblocks; extra == "development"
Requires-Dist: pyflakes; extra == "development"
Provides-Extra: distribution
Requires-Dist: build; extra == "distribution"
Requires-Dist: twine; extra == "distribution"
Requires-Dist: setup; extra == "distribution"
